edmpy/__init__.py
edmpy/__main__.py
edmpy/cfg.py
edmpy/cfg_e5.py
edmpy/constants.py
edmpy/db.py
edmpy/edm.kv
edmpy/edm.py
edmpy/geo.py
edmpy/ini.py
edmpy/py.typed
edmpy/test_edm.py
edmpy/test_message_bubbles.py
edmpy/test_nikon_bcc.py
edmpy/test_sokkia_checksum.py
edmpy/totalstation.py
edmpy/lib/__init__.py
edmpy/lib/blockdata.py
edmpy/lib/blockdata_old.py
edmpy/lib/colorscheme.py
edmpy/lib/dbs.py
edmpy/lib/e5_widgets.py
edmpy/lib/misc.py
edm_arch-1.0.50.dist-info/LICENSE
edm_arch-1.0.50.dist-info/METADATA
edm_arch-1.0.50.dist-info/WHEEL
edm_arch-1.0.50.dist-info/top_level.txt
edm_arch-1.0.50.dist-info/RECORD
