Metadata-Version: 2.1
Name: edm-arch
Version: 1.0.50
Summary: Total stations for archaeologists
Home-page: https://github.com/surf3s/EDM
Author: Shannon P. McPherron
Author-email: mcpherron@eva.mpg.de
License: MIT
Project-URL: Bug Tracker, https://github.com/surf3s/EDM/issues
Platform: unix
Platform: linux
Platform: osx
Platform: cygwin
Platform: win64
Classifier: Programming Language :: Python :: 3
Classifier: Programming Language :: Python :: 3 :: Only
Classifier: Programming Language :: Python :: 3.6
Classifier: Programming Language :: Python :: 3.7
Classifier: Programming Language :: Python :: 3.8
Classifier: Programming Language :: Python :: 3.9
Classifier: License :: OSI Approved :: MIT License
Classifier: Operating System :: OS Independent
Requires-Python: >=3.8
License-File: LICENSE
Requires-Dist: kivy>=2
Requires-Dist: tinydb>=4
Requires-Dist: pyserial>=3.5
Requires-Dist: angles>=2
Requires-Dist: pyenchant>=3.2.2
Requires-Dist: appdata>=2.2
Requires-Dist: requests>=2.31.0
Requires-Dist: platformdirs>=4.0.0
Provides-Extra: testing
Requires-Dist: pytest>=6.0; extra == "testing"
Requires-Dist: pytest-cov>=2.0; extra == "testing"
Requires-Dist: mypy>=0.910; extra == "testing"
Requires-Dist: flake8>=3.9; extra == "testing"
Requires-Dist: tox>=3.24; extra == "testing"
